vinyl2digital/__init__.py
vinyl2digital/__main__.py
vinyl2digital-1.0.6.dist-info/LICENSE
vinyl2digital-1.0.6.dist-info/METADATA
vinyl2digital-1.0.6.dist-info/WHEEL
vinyl2digital-1.0.6.dist-info/top_level.txt
vinyl2digital-1.0.6.dist-info/RECORD
