Metadata-Version: 2.1
Name: vinyl2digital
Version: 1.0.6
Summary: Batch render an audacity recording
Home-page: https://github.com/MartinBarker/vinyl2digital
Author: Martin Barker
Author-email: martinbarker99@gmail.com
Classifier: Programming Language :: Python :: 3
Classifier: License :: OSI Approved :: MIT License
Classifier: Operating System :: OS Independent
Requires-Python: >=3.6
License-File: LICENSE
Requires-Dist: requests
Requires-Dist: mutagen
